[
  {
    "kanji": "添う",
    "definition": "THIÊM そう Đi cùng, đáp ứng kì vọng"
  },
  {
    "kanji": "襲う",
    "definition": "TẬP おそう Tấn công, có cảm giác"
  },
  {
    "kanji": "慕う",
    "definition": "MỘ したう Nhớ, ngưỡng mộ"
  },
  {
    "kanji": "潤う",
    "definition": "NHUẬN うるおう Ẩm ướt, giàu có, phong phú"
  },
  {
    "kanji": "漂う",
    "definition": "PHIÊU ただよう Dạt dào, tràn trề, lềnh bềnh, trôi nổi"
  },
  {
    "kanji": "繕う",
    "definition": "THIỆN つくろう Vá"
  },
  {
    "kanji": "賄う",
    "definition": "HỐI まかなう Chịu chi trả, trang trải"
  },
  {
    "kanji": "裁く",
    "definition": "TÀI さばく Đánh giá, phán xét"
  },
  {
    "kanji": "嘆く",
    "definition": "THAN なげく Than thở, tha"
  },
  {
    "kanji": "懐く",
    "definition": "HOÀI なつく Đi theo, theo, thân thiết"
  },
  {
    "kanji": "欺く",
    "definition": "KHI あざむく Lừa gạt"
  },
  {
    "kanji": "赴く",
    "definition": "PHÓ おもむく Đi công tác"
  },
  {
    "kanji": "貫く",
    "definition": "QUAN つらぬく Xuyên qua, đi qua , giữ vững ý chí"
  },
  {
    "kanji": "継ぐ",
    "definition": "KẾ つぐ Thừa kế"
  },
  {
    "kanji": "仰ぐ",
    "definition": "NGƯỠNG あおぐ 1. nhìn lên 2. thỉnh giáo, xin ý kiến"
  },
  {
    "kanji": "揺らぐ",
    "definition": "DAO ゆらぐ 1. đung đưa 2. dao động, lung lay"
  },
  {
    "kanji": "侵す",
    "definition": "XÂM おかす Xâm phạm"
  },
  {
    "kanji": "脅す",
    "definition": "HIẾP おどす Đe dọa"
  },
  {
    "kanji": "浸す",
    "definition": "TẨM ひたす Nhúng"
  },
  {
    "kanji": "促す",
    "definition": "XÚC うながす Thúc giục, kêu gọi"
  },
  {
    "kanji": "施す",
    "definition": "THI ほどこす 1. cho, bố thí 2. tiến hành"
  },
  {
    "kanji": "催す",
    "definition": "THÔI もよおす Tổ chức"
  },
  {
    "kanji": "覆す",
    "definition": "PHÚC くつがえす 1. lật đổ 2. phủ định"
  },
  {
    "kanji": "尽くす",
    "definition": "TẬN つくす Dốc hết sức"
  },
  {
    "kanji": "脅かす",
    "definition": "HIẾP おびやかす Đe dọa"
  },
  {
    "kanji": "摘む",
    "definition": "TRÍCH つむ Ngắt, hái (hoa, cỏ)"
  },
  {
    "kanji": "挑む",
    "definition": "THIÊU いどむ Thách thức, thử sức, thử thách"
  },
  {
    "kanji": "臨む",
    "definition": "LÂM のぞむ Tiếp cận, tiến sát, tham dự"
  },
  {
    "kanji": "励む",
    "definition": "LỆ はげむ Cố gắng, phấn đấu"
  },
  {
    "kanji": "弾む",
    "definition": "ĐÀN はずむ Cái gì đó nãy lên, rộn ràng (trái tim, cảm xúc)"
  },
  {
    "kanji": "阻む",
    "definition": "TRỞ はばむ Ngăn cản, chặn , cản trở"
  },
  {
    "kanji": "謹む",
    "definition": "THẬN つつしむ Hân hạnh, kính chào"
  },
  {
    "kanji": "惜しむ",
    "definition": "TÍCH おしむ Miễn cưỡng, bịn rịn, tiết kiệm, dành dụm"
  },
  {
    "kanji": "織る",
    "definition": "CHỨC おる Dệt"
  },
  {
    "kanji": "凝る",
    "definition": "NGƯNG こる Cứng đờ (vai), say mê cái j đó, công phu tỉ mỉ đến từng chi tiết"
  },
  {
    "kanji": "擦る",
    "definition": "SÁT する Cọt xát, chà xát"
  },
  {
    "kanji": "漏る",
    "definition": "LỘ もる Dột, rò rỉ (thông tin, nước)"
  }
]